tdom/__init__.py
tdom/callables.py
tdom/escaping.py
tdom/format.py
tdom/nodes.py
tdom/parser.py
tdom/placeholders.py
tdom/processor.py
tdom/template_utils.py
tdom/tnodes.py
tdom/utils.py
tdom-0.1.14.dist-info/WHEEL
tdom-0.1.14.dist-info/METADATA
tdom-0.1.14.dist-info/RECORD
