Metadata-Version: 2.3
Name: tdom
Version: 0.1.14
Summary: A 🤘 rockin' t-string HTML templating system for Python 3.14.
Author: Dave Peck, Andrea Giammarchi, Paul Everitt
Author-email: Dave Peck <davepeck@davepeck.org>, Andrea Giammarchi <andrea.giammarchi@gmail.com>, Paul Everitt <pauleveritt@me.com>
License: MIT
Classifier: Development Status :: 2 - Pre-Alpha
Classifier: Environment :: Web Environment
Classifier: Intended Audience :: Developers
Classifier: License :: OSI Approved :: MIT License
Classifier: Operating System :: OS Independent
Classifier: Programming Language :: Python :: 3 :: Only
Classifier: Programming Language :: Python :: 3.14
Classifier: Topic :: Internet :: WWW/HTTP :: Dynamic Content
Classifier: Topic :: Text Processing :: Markup :: HTML
Classifier: Typing :: Typed
Requires-Dist: markupsafe>=3.0.3
Requires-Python: >=3.14
Project-URL: CI, https://github.com/t-strings/tdom/actions
Project-URL: Changelog, https://github.com/t-strings/tdom/releases
Project-URL: Homepage, https://github.com/t-strings/tdom
Project-URL: Issues, https://github.com/t-strings/tdom/issues
